quake_inverse_sq/__init__.py
quake_inverse_sq/_sqrt.py
quake_inverse_squareroot-0.0.4.dist-info/METADATA
quake_inverse_squareroot-0.0.4.dist-info/WHEEL
quake_inverse_squareroot-0.0.4.dist-info/top_level.txt
quake_inverse_squareroot-0.0.4.dist-info/RECORD
