Metadata-Version: 2.1
Name: quake-inverse-squareroot
Version: 0.0.4
Summary: A Python port from Quake 3's fast inverse square root algorithm
Home-page: https://github.com/timelessnesses/quake-inverse-squareroot
License: UNKNOWN
Platform: UNKNOWN
